dockie_errors/__init__.py
dockie_errors/_version.py
dockie_errors/aws.py
dockie_errors/base_exceptions.py
dockie_errors/celery.py
dockie_errors/database.py
dockie_errors/gitlab.py
dockie_errors/redis.py
dockie_errors/request.py
dockie_errors-0.1.0.dist-info/METADATA
dockie_errors-0.1.0.dist-info/WHEEL
dockie_errors-0.1.0.dist-info/top_level.txt
dockie_errors-0.1.0.dist-info/RECORD
