Metadata-Version: 2.1
Name: dockie-errors
Version: 0.1.0
Summary: Dockie Errors Python Package
Home-page: UNKNOWN
Author: Nicusor Picatureanu
Author-email: nicolaepicatureanu@gmail.com
License: UNKNOWN
Platform: UNKNOWN
Classifier: Programming Language :: Python :: 3
Classifier: Programming Language :: Python :: 3.8
Requires-Python: >=3.8
